{
  "build": {
    "content": [
      {
        "files": [
          "**/*.md",
          "**/*.yml"
        ],
        "exclude": [
          "**/obj/**",
          "**/includes/**",
          "_themes/**",
          "_themes.pdf/**",
          "**/docfx.json",
          "_repo.en-us/**",
          "README.md",
          "LICENSE",
          "LICENSE-CODE",
          "ThirdPartyNotices.md",
          "SECURITY.md"
        ]
      }
    ],
    "resource": [
      {
        "files": [
          "**/*.png",
          "**/*.jpg"
        ],
        "exclude": [
          "**/obj/**",
          "**/includes/**",
          "_themes/**",
          "_themes.pdf/**",
          "**/docfx.json",
          "_repo.en-us/**"
        ]
      }
    ],
    "overwrite": [],
    "externalReference": [],
    "globalMetadata": {
      "breadcrumb_path": "/prod_0904_PR_Sync_DS01/breadcrumb/toc.json",
      "feedback_system": "Standard",
      "permissioned-type": "public"
    },
    "fileMetadata": {},
    "template": [],
    "dest": "prod_0904_PR_Sync_DS01"
  }
}